[
    {
        "ID":1,
        "Tech":[3],
        "TechValue":[5],
        "TechUp":[5],
        "LvMax":20,
        "Name":"ui_tech12",
        "Icon":"guild_"
    },
    {
        "ID":2,
        "Tech":[4],
        "TechValue":[5],
        "TechUp":[5],
        "LvMax":20,
        "Name":"ui_tech13",
        "Icon":"guild_wf"
    },
    {
        "ID":3,
        "Tech":[5],
        "TechValue":[5],
        "TechUp":[5],
        "LvMax":20,
        "Name":"ui_tech14",
        "Icon":"guild_tg"
    },
    {
        "ID":4,
        "Tech":[6],
        "TechValue":[5],
        "TechUp":[5],
        "LvMax":20,
        "Name":"ui_tech15",
        "Icon":"guild_tf"
    },
    {
        "ID":5,
        "Tech":[2],
        "TechValue":[100],
        "TechUp":[100],
        "LvMax":20,
        "Name":"ui_tech16",
        "Icon":"guild_sm"
    }
]

